hdtorch/HDVecGenerators.py
hdtorch/HDencoding.py
hdtorch/HDmodel.py
hdtorch/HDutil.py
hdtorch/__init__.py
hdtorch/cuda/hdtorch.cpp
hdtorch/cuda/hdtorch_cu.cu
hdtorch/version.py
hdtorch-1.1.0.dist-info/WHEEL
hdtorch-1.1.0.dist-info/METADATA
hdtorch-1.1.0.dist-info/RECORD
