Metadata-Version: 2.1
Name: hdtorch
Version: 1.1.0
Summary: HDTorch: Accelerating Hyperdimensional Computing with GP-GPUs for Design Space Exploration
Home-page: https://c4science.ch/source/hdtorch/
License: MIT
Author: wasimon
Author-email: william.simon@epfl.ch
Requires-Python: >=3.6,<4.0
Classifier: License :: OSI Approved :: MIT License
Classifier: Programming Language :: Python :: 3
Classifier: Programming Language :: Python :: 3.6
Classifier: Programming Language :: Python :: 3.7
Classifier: Programming Language :: Python :: 3.8
Classifier: Programming Language :: Python :: 3.9
Classifier: Programming Language :: Python :: 3.10
Classifier: Programming Language :: Python :: 3.11
Project-URL: Documentation, https://hdtorch.readthedocs.io/en/latest/
Project-URL: Repository, https://c4science.ch/source/hdtorch/
